{
  "type": "object",
  "properties": {
    "deposit-read": {
      "type": "object",
      "properties": {
        "roles": {
          "type": "array",
          "items": {
            "type": "number"
          }
        },
        "user": {
          "type": "array",
          "items": {
            "type": "number"
          }
        }
      }
    },
    "deposit-admin": {
      "type": "object",
      "properties": {
        "roles": {
          "type": "array",
          "items": {
            "type": "number"
          }
        },
        "user": {
          "type": "array",
          "items": {
            "type": "number"
          }
        }
      }
    },
    "deposit-update": {
      "type": "object",
      "properties": {
        "roles": {
          "type": "array",
          "items": {
            "type": "number"
          }
        },
        "user": {
          "type": "array",
          "items": {
            "type": "number"
          }
        }
      }
    }
  }
}